Metadata-Version: 1.0
Name: rescaleforvis
Version: 1.0
Summary: Maps each number of a short list to a whole number, such that the order of the magnitudes of the differences between any two numbers is preserved.
Home-page: https://github.com/garryFromGermany/rescale_for_vis
Author: Garrett May
Author-email: garrettmay@live.de
License: MIT
Platform: UNKNOWN
